bc_time/__init__.py
bc_time/api/__init__.py
bc_time/api/api.py
bc_time/api/constants/__init__.py
bc_time/api/constants/api.py
bc_time/api/enumerators/__init__.py
bc_time/api/enumerators/api_authorisation_type.py
bc_time/api/enumerators/content_type.py
bc_time/api/enumerators/device_communication_type.py
bc_time/api/enumerators/request_status.py
bc_time/api/enumerators/status.py
bc_time/api/objects/__init__.py
bc_time/api/objects/api_authorisations.py
bc_time/api/objects/base.py
bc_time/api/objects/branches.py
bc_time/api/objects/company_profiles.py
bc_time/api/objects/controllers.py
bc_time/api/objects/daily_overtime_data.py
bc_time/api/objects/departments.py
bc_time/api/objects/devices.py
bc_time/api/objects/employee_leave.py
bc_time/api/objects/employees.py
bc_time/api/objects/group_base.py
bc_time/api/objects/object_base.py
bc_time/api/objects/object_base_create.py
bc_time/api/objects/object_base_read.py
bc_time/api/objects/object_base_update.py
bc_time/api/objects/object_base_write.py
bc_time/api/objects/period_overtime_data.py
bc_time/api/objects/raw_attendance.py
bc_time/api/objects/settings.py
bc_time/api/objects/visitor_groups.py
bc_time/api/objects/visitors.py
bc_time/oauth2/__init__.py
bc_time/oauth2/token.py
bc_time/oauth2/constants/__init__.py
bc_time/oauth2/constants/grant_type.py
bc_time/requests/__init__.py
bc_time/requests/base.py
bc_time/system/__init__.py
bc_time/system/validate.py
bc_time/system/constants/__init__.py
bc_time/system/constants/datetime/__init__.py
bc_time/system/constants/datetime/format.py
bc_time/system/constants/encryption/__init__.py
bc_time/system/constants/encryption/crypt.py
bc_time/system/encryption/__init__.py
bc_time/system/encryption/crypt.py
bc_time-8.1.0.dist-info/LICENSE.txt
bc_time-8.1.0.dist-info/METADATA
bc_time-8.1.0.dist-info/WHEEL
bc_time-8.1.0.dist-info/top_level.txt
bc_time-8.1.0.dist-info/RECORD
