Metadata-Version: 2.1
Name: bc_time
Version: 8.1.0
Summary: SDK that helps with integration via the Binary City Time API.
Home-page: https://github.com/Binary-City/bc_time_api_sdk
Author: Darius Burger
Author-email: darius@bcity.me
License: MIT
Classifier: Programming Language :: Python :: 3
Classifier: License :: OSI Approved :: MIT License
Classifier: Operating System :: OS Independent
Requires-Python: >=3.10
License-File: LICENSE.txt
Requires-Dist: cryptography
Requires-Dist: requests
